rez/__init__.py
rez/build_process.py
rez/build_system.py
rez/bundle_context.py
rez/command.py
rez/config.py
rez/deprecations.py
rez/developer_package.py
rez/exceptions.py
rez/package_bind.py
rez/package_cache.py
rez/package_copy.py
rez/package_filter.py
rez/package_help.py
rez/package_maker.py
rez/package_move.py
rez/package_order.py
rez/package_py_utils.py
rez/package_remove.py
rez/package_repository.py
rez/package_resources.py
rez/package_search.py
rez/package_serialise.py
rez/package_test.py
rez/packages.py
rez/pip.py
rez/plugin_managers.py
rez/release_hook.py
rez/release_vcs.py
rez/resolved_context.py
rez/resolver.py
rez/rex.py
rez/rex_bindings.py
rez/rezconfig.py
rez/serialise.py
rez/shells.py
rez/solver.py
rez/status.py
rez/suite.py
rez/system.py
rez/util.py
rez/wrapper.py
rez/bind/PyQt.py
rez/bind/PySide.py
rez/bind/__init__.py
rez/bind/_pymodule.py
rez/bind/_utils.py
rez/bind/arch.py
rez/bind/cmake.py
rez/bind/gcc.py
rez/bind/hello_world.py
rez/bind/os.py
rez/bind/pip.py
rez/bind/platform.py
rez/bind/python.py
rez/bind/rez.py
rez/bind/rezgui.py
rez/bind/setuptools.py
rez/bind/sip.py
rez/cli/__init__.py
rez/cli/_complete_util.py
rez/cli/_entry_points.py
rez/cli/_main.py
rez/cli/_util.py
rez/cli/benchmark.py
rez/cli/bind.py
rez/cli/build.py
rez/cli/bundle.py
rez/cli/complete.py
rez/cli/config.py
rez/cli/context.py
rez/cli/cp.py
rez/cli/depends.py
rez/cli/diff.py
rez/cli/env.py
rez/cli/forward.py
rez/cli/gui.py
rez/cli/help.py
rez/cli/interpret.py
rez/cli/memcache.py
rez/cli/mv.py
rez/cli/pip.py
rez/cli/pkg-cache.py
rez/cli/pkg-ignore.py
rez/cli/plugins.py
rez/cli/python.py
rez/cli/release.py
rez/cli/rm.py
rez/cli/search.py
rez/cli/selftest.py
rez/cli/status.py
rez/cli/suite.py
rez/cli/test.py
rez/cli/view.py
rez/cli/yaml2py.py
rez/completion/complete.csh
rez/completion/complete.sh
rez/completion/complete.zsh
rez/data/benchmarking/packages.tar.gz
rez/data/benchmarking/requests.json
rez/data/tests/bind/__init__.py
rez/data/tests/bind/os.py
rez-3.3.0.dist-info/licenses/LICENSE
rez-3.3.0.dist-info/METADATA
rez-3.3.0.dist-info/WHEEL
rez-3.3.0.dist-info/entry_points.txt
rez-3.3.0.dist-info/top_level.txt
rez/data/tests/extensions/baz/baz-0.1.0.dist-info/METADATA
rez/data/tests/extensions/baz/baz-0.1.0.dist-info/entry_points.txt
rez/data/tests/pip/installed_distributions/six-1.12.0.dist-info/INSTALLER
rez/data/tests/pip/installed_distributions/six-1.12.0.dist-info/LICENSE
rez/data/tests/pip/installed_distributions/six-1.12.0.dist-info/METADATA
rez/data/tests/pip/installed_distributions/six-1.12.0.dist-info/RECORD
rez/data/tests/pip/installed_distributions/six-1.12.0.dist-info/WHEEL
rez/data/tests/pip/installed_distributions/six-1.12.0.dist-info/top_level.txt
rez-3.3.0.dist-info/RECORD
