Metadata-Version: 2.4
Name: rez
Version: 3.3.0
Summary: A cross-platform packaging system that can build and install multiple version of packages, and dynamically configure resolved environments at runtime.
Home-page: https://github.com/AcademySoftwareFoundation/rez
Author: Allan Johns
Author-email: nerdvegas@gmail.com
Maintainer: Contributors to the rez project
Maintainer-email: rez-discussion@lists.aswf.io
License: Apache-2.0
Keywords: package resolve version build install software management
Classifier: Development Status :: 5 - Production/Stable
Classifier: License :: OSI Approved :: Apache Software License
Classifier: Intended Audience :: Developers
Classifier: Operating System :: OS Independent
Classifier: Programming Language :: Python
Classifier: Programming Language :: Python :: 3.8
Classifier: Programming Language :: Python :: 3.9
Classifier: Programming Language :: Python :: 3.10
Classifier: Programming Language :: Python :: 3.11
Classifier: Programming Language :: Python :: 3.12
Classifier: Programming Language :: Python :: 3.13
Classifier: Topic :: Software Development
Classifier: Topic :: System :: Software Distribution
Requires-Python: >=3.8
License-File: LICENSE
Dynamic: author
Dynamic: author-email
Dynamic: classifier
Dynamic: description
Dynamic: description-content-type
Dynamic: home-page
Dynamic: keywords
Dynamic: license
Dynamic: license-file
Dynamic: maintainer
Dynamic: maintainer-email
Dynamic: requires-python
Dynamic: summary
